topsis/__init__.py
topsis/topsis.py
topsis_102197016-1.1.2.dist-info/LICENSE.txt
topsis_102197016-1.1.2.dist-info/METADATA
topsis_102197016-1.1.2.dist-info/WHEEL
topsis_102197016-1.1.2.dist-info/entry_points.txt
topsis_102197016-1.1.2.dist-info/top_level.txt
topsis_102197016-1.1.2.dist-info/RECORD
